{
  "artigo_id": "ART_005",
  "arquivo": "Applying Machine Learning to the Fuel Theft Problem on Pipelines.pdf",
  "analysis": [
    {
      "page_num": 1,
      "strategy": "text",
      "reason": "Primeira página (metadados)",
      "text_until": null
    },
    {
      "page_num": 2,
      "strategy": "text",
      "reason": "Somente texto",
      "text_until": null
    },
    {
      "page_num": 3,
      "strategy": "image",
      "reason": "Contém figuras/tabelas/gráficos",
      "text_until": null
    },
    {
      "page_num": 4,
      "strategy": "text",
      "reason": "Somente texto",
      "text_until": null
    },
    {
      "page_num": 5,
      "strategy": "text",
      "reason": "Somente texto",
      "text_until": null
    },
    {
      "page_num": 6,
      "strategy": "image",
      "reason": "Contém figuras/tabelas/gráficos",
      "text_until": null
    },
    {
      "page_num": 7,
      "strategy": "image",
      "reason": "Contém figuras/tabelas/gráficos",
      "text_until": null
    },
    {
      "page_num": 8,
      "strategy": "text",
      "reason": "Somente texto",
      "text_until": null
    },
    {
      "page_num": 9,
      "strategy": "image",
      "reason": "Contém figuras/tabelas/gráficos",
      "text_until": null
    },
    {
      "page_num": 10,
      "strategy": "text_partial",
      "reason": "Texto parcial (até referências)",
      "text_until": 585
    }
  ],
  "stats": {
    "total": 10,
    "text_pages": 6,
    "image_pages": 4,
    "skipped_pages": 0
  },
  "pages_info": [
    {
      "page_num": 1,
      "type": "text",
      "path": null
    },
    {
      "page_num": 2,
      "type": "text",
      "path": null
    },
    {
      "page_num": 3,
      "type": "image",
      "path": "C:\\Users\\Leonardo\\Documents\\Computing\\Projeto_Mestrado\\files\\files\\articles\\00 Dados RSL\\Extraction\\outputs\\work\\ART_005\\pages\\page_003.png"
    },
    {
      "page_num": 4,
      "type": "text",
      "path": null
    },
    {
      "page_num": 5,
      "type": "text",
      "path": null
    },
    {
      "page_num": 6,
      "type": "image",
      "path": "C:\\Users\\Leonardo\\Documents\\Computing\\Projeto_Mestrado\\files\\files\\articles\\00 Dados RSL\\Extraction\\outputs\\work\\ART_005\\pages\\page_006.png"
    },
    {
      "page_num": 7,
      "type": "image",
      "path": "C:\\Users\\Leonardo\\Documents\\Computing\\Projeto_Mestrado\\files\\files\\articles\\00 Dados RSL\\Extraction\\outputs\\work\\ART_005\\pages\\page_007.png"
    },
    {
      "page_num": 8,
      "type": "text",
      "path": null
    },
    {
      "page_num": 9,
      "type": "image",
      "path": "C:\\Users\\Leonardo\\Documents\\Computing\\Projeto_Mestrado\\files\\files\\articles\\00 Dados RSL\\Extraction\\outputs\\work\\ART_005\\pages\\page_009.png"
    },
    {
      "page_num": 10,
      "type": "text",
      "path": null
    }
  ]
}